papers_please/__init__.py
papers_please/client/OpenAlexAPIClient.py
papers_please/client/OrcidAPIClient.py
papers_please/client/ScopusAPIClient.py
papers_please/core/Metrics.py
papers_please/core/ResearchGroup.py
papers_please/core/Researcher.py
papers_please/data/OrcidAPIDataParser.py
papers_please/data/XMLParser.py
papers_please/tests/__init__.py
papers_please/tests/test_openalex_api_client_integration.py
papers_please/tests/test_orcid_api_client_integration.py
papers_please/tests/test_scopus_api_client_integration.py
papers_please-1.1.1.dist-info/METADATA
papers_please-1.1.1.dist-info/WHEEL
papers_please-1.1.1.dist-info/top_level.txt
papers_please-1.1.1.dist-info/RECORD
