Metadata-Version: 2.4
Name: papers-please
Version: 1.1.1
Summary: A comprehensive Python library for retrieving and analyzing researcher data from ORCID and converting Lattes XML files to BibTeX format
Author: Henrique Marques, Gabriel Barbosa, Renato Spessoto, Henrique Gomes, Eduardo Neves
Maintainer-email: Gabriel Barbosa <gabriel_barbosa@usp.br>
Project-URL: Repository, https://github.com/EngSoft2025/orcid-project-papers-please
Project-URL: Issues, https://github.com/EngSoft2025/orcid-project-papers-please/issues
Keywords: orcid,research,publications,bibtex,lattes,academic,citations,researcher,bibliography,scopus,openalex
Classifier: Development Status :: 4 - Beta
Classifier: Intended Audience :: Science/Research
Classifier: Intended Audience :: Developers
Classifier: Operating System :: OS Independent
Classifier: Programming Language :: Python :: 3.10
Classifier: Programming Language :: Python :: 3.11
Classifier: Programming Language :: Python :: 3.12
Classifier: Topic :: Scientific/Engineering
Classifier: Topic :: Software Development :: Libraries :: Python Modules
Classifier: Topic :: Internet :: WWW/HTTP :: Dynamic Content
Classifier: Topic :: Text Processing :: Markup :: XML
Requires-Python: >=3.10
Requires-Dist: certifi==2025.4.26
Requires-Dist: charset-normalizer==3.4.2
Requires-Dist: defusedxml>=0.7.1
Requires-Dist: idna==3.10
Requires-Dist: numpy==2.2.5
Requires-Dist: pandas==2.2.3
Requires-Dist: python-dateutil==2.9.0.post0
Requires-Dist: pytz==2025.2
Requires-Dist: requests==2.32.3
Requires-Dist: six==1.17.0
Requires-Dist: tzdata==2024.2
Requires-Dist: urllib3==2.4.0
